ttperf/__init__.py
ttperf/ttperf.py
ttperf/data/operation_configs.json
ttperf/data/test_eltwise_operations.py
ttperf-0.1.6.dist-info/licenses/LICENSE
ttperf-0.1.6.dist-info/METADATA
ttperf-0.1.6.dist-info/WHEEL
ttperf-0.1.6.dist-info/entry_points.txt
ttperf-0.1.6.dist-info/top_level.txt
ttperf-0.1.6.dist-info/RECORD
