Metadata-Version: 2.4
Name: ttperf
Version: 0.1.6
Summary: A Python CLI wrapper for profiling Tenstorrent's TT-Metal tests
Author-email: Aswin <aswin@aswincloud.com>
License: MIT License
Project-URL: Homepage, https://github.com/Aswintechie/ttperf
Project-URL: Repository, https://github.com/Aswintechie/ttperf
Project-URL: Issues, https://github.com/Aswintechie/ttperf/issues
Project-URL: Documentation, https://github.com/Aswintechie/ttperf/blob/master/README.md
Keywords: tenstorrent,tt-metal,profiling,performance,cli
Classifier: Development Status :: 4 - Beta
Classifier: Intended Audience :: Developers
Classifier: Programming Language :: Python :: 3
Classifier: Programming Language :: Python :: 3.8
Classifier: Programming Language :: Python :: 3.9
Classifier: Programming Language :: Python :: 3.10
Classifier: Programming Language :: Python :: 3.11
Classifier: Topic :: Software Development :: Testing
Classifier: Topic :: System :: Benchmark
Requires-Python: >=3.8
License-File: LICENSE
Requires-Dist: pandas>=1.3.0
Dynamic: license-file
